landmark/__init__.py
landmark/__version__.py
landmark/datasets.py
landmark/k_center.py
landmark/maxmin.cpython-312-x86_64-linux-gnu.so
landmark/maxmin.py
scikit_landmark-0.1.2.dist-info/LICENSE
scikit_landmark-0.1.2.dist-info/METADATA
scikit_landmark-0.1.2.dist-info/WHEEL
scikit_landmark-0.1.2.dist-info/RECORD
