Metadata-Version: 2.1
Name: scikit-landmark
Version: 0.1.2
Author-Email: Matt Piekenbrock <matt.piekenbrock@gmail.com>
License:                                  Apache License
Classifier: Intended Audience :: Science/Research
Classifier: Development Status :: 3 - Alpha
Classifier: License :: OSI Approved :: Apache Software License
Classifier: Programming Language :: Python :: 3
Requires-Python: >=3.8
Requires-Dist: numpy
Provides-Extra: test
Requires-Dist: scipy; extra == "test"
Requires-Dist: pytest; extra == "test"
Requires-Dist: coveralls; extra == "test"
Requires-Dist: coverage; extra == "test"
Requires-Dist: pytest-cov; extra == "test"
